cooar_cli.py
cooar_cli-0.2.0.dist-info/entry_points.txt
cooar_cli-0.2.0.dist-info/LICENSE
cooar_cli-0.2.0.dist-info/WHEEL
cooar_cli-0.2.0.dist-info/METADATA
cooar_cli-0.2.0.dist-info/RECORD
