Metadata-Version: 2.1
Name: cooar-cli
Version: 0.2.0
Summary: 
Home-page: https://github.com/chrisWhyTea/cooar-cli
License: BSD-3-Clause
Author: Christopher Schmitt
Author-email: cooar@chris.yt
Requires-Python: >=3.8,<4.0
Classifier: License :: OSI Approved :: BSD License
Classifier: Programming Language :: Python :: 3
Classifier: Programming Language :: Python :: 3.8
Requires-Dist: MechanicalSoup (>=0.12.0,<0.13.0)
Requires-Dist: arrow (>=0.15.5,<0.16.0)
Requires-Dist: click (>=7.0,<8.0)
Requires-Dist: colorama (>=0.4.3,<0.5.0)
Requires-Dist: jinja2 (>=2.11.1,<3.0.0)
Project-URL: Repository, https://github.com/chrisWhyTea/cooar-cli
